customtkinter/__init__.py
customtkinter/assets/.DS_Store
customtkinter/assets/fonts/CustomTkinter_shapes_font.otf
customtkinter/assets/fonts/Roboto/Roboto-Medium.ttf
customtkinter/assets/fonts/Roboto/Roboto-Regular.ttf
customtkinter/assets/icons/.DS_Store
customtkinter/assets/icons/CustomTkinter_icon_Windows.ico
customtkinter/assets/themes/blue.json
customtkinter/assets/themes/dark-blue.json
customtkinter/assets/themes/green.json
customtkinter/windows/__init__.py
customtkinter/windows/ctk_input_dialog.py
customtkinter/windows/ctk_tk.py
customtkinter/windows/ctk_toplevel.py
customtkinter/windows/widgets/__init__.py
customtkinter/windows/widgets/ctk_button.py
customtkinter/windows/widgets/ctk_checkbox.py
customtkinter/windows/widgets/ctk_combobox.py
customtkinter/windows/widgets/ctk_entry.py
customtkinter/windows/widgets/ctk_frame.py
customtkinter/windows/widgets/ctk_label.py
customtkinter/windows/widgets/ctk_optionmenu.py
customtkinter/windows/widgets/ctk_progressbar.py
customtkinter/windows/widgets/ctk_radiobutton.py
customtkinter/windows/widgets/ctk_scrollable_frame.py
customtkinter/windows/widgets/ctk_scrollbar.py
customtkinter/windows/widgets/ctk_segmented_button.py
customtkinter/windows/widgets/ctk_slider.py
customtkinter/windows/widgets/ctk_switch.py
customtkinter/windows/widgets/ctk_tabview.py
customtkinter/windows/widgets/ctk_textbox.py
customtkinter/windows/widgets/appearance_mode/__init__.py
customtkinter/windows/widgets/appearance_mode/appearance_mode_base_class.py
customtkinter/windows/widgets/appearance_mode/appearance_mode_tracker.py
customtkinter/windows/widgets/core_rendering/__init__.py
customtkinter/windows/widgets/core_rendering/ctk_canvas.py
customtkinter/windows/widgets/core_rendering/draw_engine.py
customtkinter/windows/widgets/core_widget_classes/__init__.py
customtkinter/windows/widgets/core_widget_classes/ctk_base_class.py
customtkinter/windows/widgets/core_widget_classes/dropdown_menu.py
customtkinter/windows/widgets/font/__init__.py
customtkinter-5.2.1.dist-info/LICENSE
customtkinter-5.2.1.dist-info/METADATA
customtkinter-5.2.1.dist-info/WHEEL
customtkinter-5.2.1.dist-info/top_level.txt
customtkinter-5.2.1.dist-info/RECORD
